{
  "headers": {
    "x-amz-version-id": "rDPmxxiNyiTVA17Os0fDQGw4_hwJaff7",
    "content-type": "application/typescript; charset=utf-8",
    "access-control-allow-origin": "*",
    "etag": "\"0e5d83e985fb0afd2b1e5e752f4efdbd\"",
    "cache-control": "public, max-age=31536000, immutable",
    "content-length": "84",
    "date": "Sun, 27 Mar 2022 08:46:00 GMT",
    "x-amz-id-2": "PcQl13ROqNPVzx5oTpe2+uCc0nMfMvTlx1F76bGMLfSCasJs+DinVype9+4f2jzj64zMicKBu24=",
    "server": "deploy/northamerica-northeast2-c",
    "last-modified": "Wed, 13 Oct 2021 14:41:10 GMT",
    "x-amz-request-id": "FXG0WSAZQ02QWN0S"
  },
  "url": "https://deno.land/x/redis@v0.25.0/protocol/_util.ts",
  "now": {
    "secs_since_epoch": 1648370759,
    "nanos_since_epoch": 125033597
  }
}