{
  "headers": {
    "content-type": "application/typescript; charset=utf-8",
    "cf-ray": "671513aa4fd7c16b-IAD",
    "x-amz-version-id": "NSbs1ws0EqmHbYAVoeRK8w_ZA.j3AG7Z",
    "server": "cloudflare",
    "alt-svc": "h3-27=\":443\"; ma=86400, h3-28=\":443\"; ma=86400, h3-29=\":443\"; ma=86400, h3=\":443\"; ma=86400",
    "cf-cache-status": "DYNAMIC",
    "date": "Mon, 19 Jul 2021 15:45:26 GMT",
    "last-modified": "Wed, 16 Jun 2021 22:07:16 GMT",
    "via": "HTTP/1.1 deploy",
    "x-amz-request-id": "CWJ1XYDZ2GSBSGBN",
    "etag": "\"14f1d50164a7fc21c3f67cb77a88ce5e\"",
    "x-amz-id-2": "stx61Z8l4H2TF55goeUaPuf1w8g9WTsH2rG2wddvttgCNjbDWOeZO/jo9hEbSqLUolkmDqlyewQ=",
    "x-deno-ray": "us-east4-c::d3083618c41bd117d599f42913cbf73e",
    "content-length": "2547",
    "expect-ct": "max-age=604800, report-uri=\"https://report-uri.cloudflare.com/cdn-cgi/beacon/expect-ct\"",
    "cache-control": "public, max-age=31536000, immutable",
    "access-control-allow-origin": "*",
    "vary": "Accept-Encoding"
  },
  "url": "https://deno.land/x/cliffy@v0.19.2/ansi/ansi.ts"
}