{
  "headers": {
    "cache-control": "public, max-age=31536000, immutable",
    "date": "Sat, 26 Mar 2022 23:13:12 GMT",
    "x-amz-id-2": "1sytXDWAhAY1fdya/ve6cx4h+iQiKbVuG5WTmmJtlZG8WAsd5XuteG65VzJ9icuqPZ5JmMui8Qw=",
    "content-length": "971",
    "server": "deploy/northamerica-northeast2-c",
    "content-type": "application/typescript; charset=utf-8",
    "x-amz-request-id": "1H876549ZCVCRNFZ",
    "x-amz-version-id": "farMwuQZ96t8ymcG7em3fVZz8MYhvFvC",
    "etag": "\"5b69a803fd7aef6c33cf095e18f000f4\"",
    "last-modified": "Fri, 14 Jan 2022 21:47:05 GMT",
    "access-control-allow-origin": "*"
  },
  "url": "https://deno.land/x/postgres@v0.15.0/connection/auth.ts",
  "now": {
    "secs_since_epoch": 1648336391,
    "nanos_since_epoch": 579680989
  }
}