{
  "headers": {
    "cache-control": "public, max-age=31536000, immutable",
    "date": "Sun, 08 Aug 2021 20:56:59 GMT",
    "access-control-allow-origin": "*",
    "server": "AmazonS3",
    "x-deno-ray": "northamerica-northeast1-b::c04c36f4d0356b4022ed1c44b74185c8",
    "x-amz-request-id": "RZHZ43WYPM2DNG11",
    "content-type": "application/typescript; charset=utf-8",
    "last-modified": "Mon, 19 Jul 2021 17:53:25 GMT",
    "via": "HTTP/1.1 deploy",
    "content-length": "1945",
    "etag": "\"750ae0df3aaa0c8fdff773c40588fc59\"",
    "x-amz-version-id": "X4z.ntDrs99.hQgJFznSNAPsxpSzU.rg",
    "x-amz-id-2": "vOCDeCOQHoCVEqrwKMbWcDNrVVaUPUMwQ2f6cN/15LSUny9TihUI6vbU6jruPIFotJZIPyT9qWg="
  },
  "url": "https://deno.land/std@0.102.0/path/_constants.ts"
}