{
  "headers": {
    "accept-ranges": "bytes",
    "x-amz-id-2": "gdtzUruJbg8k0eCMgjlzDPniQYknjPny2gnrgOMM9bGC27u6OwQ89y5Vlana/eL/p3O11Z3emVc=",
    "server": "cloudflare",
    "x-amz-version-id": "rO9TCMGyaz8b_WS2kqCEDsdGqLTGBTpP",
    "age": "435171",
    "etag": "\"49753f0d9c749add470ce5904420d7e9\"",
    "x-amz-request-id": "T4A4YF5XJA4YQ2WZ",
    "alt-svc": "h3-27=\":443\"; ma=86400, h3-28=\":443\"; ma=86400, h3-29=\":443\"; ma=86400, h3=\":443\"; ma=86400",
    "content-type": "application/typescript; charset=utf-8",
    "content-length": "14619",
    "cf-ray": "6693d86ead2a596e-IAD",
    "cache-control": "public, max-age=31536000, immutable",
    "last-modified": "Tue, 15 Jun 2021 20:18:59 GMT",
    "vary": "Accept-Encoding",
    "date": "Sat, 03 Jul 2021 23:20:36 GMT",
    "cf-cache-status": "HIT",
    "access-control-allow-origin": "*",
    "expect-ct": "max-age=604800, report-uri=\"https://report-uri.cloudflare.com/cdn-cgi/beacon/expect-ct\""
  },
  "url": "https://deno.land/std@0.99.0/path/posix.ts"
}