{
  "headers": {
    "content-length": "4844",
    "last-modified": "Tue, 15 Jun 2021 20:18:57 GMT",
    "accept-ranges": "bytes",
    "age": "430486",
    "content-type": "application/typescript; charset=utf-8",
    "expect-ct": "max-age=604800, report-uri=\"https://report-uri.cloudflare.com/cdn-cgi/beacon/expect-ct\"",
    "x-amz-id-2": "shxcg03rBHgs1OwIoofnUGBo8apAm0QRVio9HD2NhH2J0489hPa3lVzthXJWLS5QaGFgS5nuUkg=",
    "vary": "Accept-Encoding",
    "cache-control": "public, max-age=31536000, immutable",
    "etag": "\"66df38fec40bbeff487e8d4ee66c7ddc\"",
    "x-amz-request-id": "60D3J5XGWEB96GDH",
    "server": "cloudflare",
    "alt-svc": "h3-27=\":443\"; ma=86400, h3-28=\":443\"; ma=86400, h3-29=\":443\"; ma=86400, h3=\":443\"; ma=86400",
    "date": "Sun, 04 Jul 2021 00:07:36 GMT",
    "cf-ray": "66941d477f795dc2-IAD",
    "cf-cache-status": "HIT",
    "x-amz-version-id": "qNi25tpEaVN.7789F9RdPhR.r8rCw8cU",
    "access-control-allow-origin": "*"
  },
  "url": "https://deno.land/std@0.99.0/bytes/mod.ts"
}